mbtestpackage
