Metadata-Version: 1.0
Name: mbtestpackage
Version: 0.01.09
Summary: my test package
Home-page: http://pypi.python.org/pypi/mbtestpackage/
Author: Alectryon LLC
Author-email: mbiedler@gmail.com
License: license.txt
Platform: UNKNOWN
